stcog/__init__.py
stcog/auth.py
stcog/exceptions.py
stcog/session_provider.py
stcog/utils.py
stcog-0.0.7.dist-info/METADATA
stcog-0.0.7.dist-info/WHEEL
stcog-0.0.7.dist-info/licenses/LICENSE
stcog-0.0.7.dist-info/RECORD
