Metadata-Version: 2.3
Name: stcog
Version: 0.0.7
Summary: A package for streamlit and aws auth link
Project-URL: Homepage, https://github.com/pop-srw/streamlit-cognito-auth/
Project-URL: Issues, https://github.com/pop-srw/streamlit-cognito-auth/issues
Author-email: Pastoris Zumba <fcuy047@gmail.com>
License-File: LICENSE
Classifier: License :: OSI Approved :: MIT License
Classifier: Operating System :: OS Independent
Classifier: Programming Language :: Python :: 3
Requires-Python: >=3.8
Requires-Dist: boto3==1.34.40
Requires-Dist: pycognito==2024.1.0
Requires-Dist: streamlit==1.31.1
